{"cameraMode":{"drawMode":0,"name":"Shaded","section":"Shading Mode"},"sceneLighting":false,"audioPlay":false,"sceneViewState":{"m_AlwaysRefresh":false,"showFog":true,"showSkybox":false,"showFlares":true,"showImageEffects":true,"showParticleSystems":true,"showVisualEffectGraphs":true,"m_FxEnabled":true},"in2DMode":false,"pivot":{"x":-0.5395256876945496,"y":0.652655839920044,"z":-3.992182970046997},"rotation":{"x":0.19549080729484559,"y":0.02384764887392521,"z":-0.004716509487479925,"w":0.980459451675415},"size":1.286729335784912,"orthographic":false}